azure_blob_utils/__init__.py
azure_blob_utils/azure_blob_utils.py
mar_azure_blob_utils-0.3.dist-info/LICENSE
mar_azure_blob_utils-0.3.dist-info/METADATA
mar_azure_blob_utils-0.3.dist-info/WHEEL
mar_azure_blob_utils-0.3.dist-info/top_level.txt
mar_azure_blob_utils-0.3.dist-info/RECORD
