Metadata-Version: 2.1
Name: mar-azure-blob-utils
Version: 0.3
Summary: A wrapper libray for Azure Blob Storage
Home-page: https://github.com/maradder/azure_blob_utils
Author: Marcus Radder
Author-email: marcusradder@gmail.com
License: MIT
Classifier: Programming Language :: Python :: 3
Classifier: License :: OSI Approved :: MIT License
Classifier: Operating System :: OS Independent
License-File: LICENSE
Requires-Dist: azure-storage-blob
